Pyaesar/Emperor.py
Pyaesar/Legionnaire.py
Pyaesar/Legions.py
Pyaesar/__init__.py
Pyaesar/utils.py
Pyaesar-1.0.3.dist-info/LICENSE
Pyaesar-1.0.3.dist-info/METADATA
Pyaesar-1.0.3.dist-info/WHEEL
Pyaesar-1.0.3.dist-info/top_level.txt
Pyaesar-1.0.3.dist-info/RECORD
