Metadata-Version: 2.1
Name: Pyaesar
Version: 1.0.3
Summary: Data Parallelized MultiNoded Distributed Interface
Home-page: https://gitlab.com/jamilggafur/pyaesar
Author: Jamil Gafur, Geoffery Fairchild, Carrie Manore, Katherine Kempfert
Author-email: jamilgafur@gmail.com
Maintainer: Jamil Gafur
Maintainer-email: jamilgafur@gmail.com
License: BSD
Platform: UNKNOWN
Classifier: Development Status :: 3 - Alpha
Classifier: Intended Audience :: Developers
Classifier: Intended Audience :: Science/Research
Classifier: License :: OSI Approved :: BSD License
Classifier: Operating System :: OS Independent
Classifier: Intended Audience :: Education
Classifier: Intended Audience :: End Users/Desktop
Classifier: Programming Language :: Python :: 2
Classifier: Programming Language :: Python :: 2.7
Classifier: Programming Language :: Python :: 3
Classifier: Topic :: Software Development :: Libraries :: Python Modules
Requires-Dist: mpi4py
Requires-Dist: multiprocess
